sqlplate/__init__.py
sqlplate/__version__.py
sqlplate/conf.py
sqlplate/exceptions.py
sqlplate/sqlplate.py
sqlplate/utils.py
sqlplate-0.0.7.dist-info/licenses/LICENSE
sqlplate-0.0.7.dist-info/WHEEL
sqlplate-0.0.7.dist-info/METADATA
sqlplate-0.0.7.dist-info/RECORD
