Metadata-Version: 2.4
Name: sqlplate
Version: 0.0.7
Summary: SQL template generator
Keywords: utility,sql
Author-email: korawica <korawich.anu@gmail.com>
Requires-Python: >= 3.10
Classifier: Topic :: Utilities
Classifier: Natural Language :: English
Classifier: Development Status :: 4 - Beta
Classifier: Operating System :: OS Independent
Classifier: License :: OSI Approved :: MIT License
Classifier: Programming Language :: Python
Classifier: Programming Language :: Python :: 3 :: Only
Classifier: Programming Language :: Python :: 3.10
Classifier: Programming Language :: Python :: 3.11
Classifier: Programming Language :: Python :: 3.12
Classifier: Programming Language :: Python :: 3.13
Classifier: Typing :: Typed
License-File: LICENSE
Requires-Dist: Jinja2>=3.1.6,<4.0.0
Project-URL: Homepage, https://github.com/korawica/sqlplate/
Project-URL: Source, https://github.com/korawica/sqlplate/
